neighborhood_correlation/__init__.py
neighborhood_correlation/dictarray.py
neighborhood_correlation/nc_base.py
neighborhood_correlation/nchelparr.cpython-312-darwin.so
neighborhood_correlation/nchelparr_python.py
neighborhood_correlation/tool.py
neighborhood_correlation-2.2.dist-info/LICENSE
neighborhood_correlation-2.2.dist-info/METADATA
neighborhood_correlation-2.2.dist-info/WHEEL
neighborhood_correlation-2.2.dist-info/entry_points.txt
neighborhood_correlation-2.2.dist-info/top_level.txt
neighborhood_correlation-2.2.dist-info/RECORD
