Metadata-Version: 2.1
Name: neighborhood_correlation
Version: 2.2
Summary: Protein sequence similarity assessment by assessing variance of sequences' scores to _other_ sequences
Author-email: Jacob Joseph <jmjoseph@andrew.cmu.edu>
Maintainer-email: Lars Arvestad <arve@math.su.se>
License: GNU General Public License v3 (GPLv3)
Project-URL: homepage, http://www.neighborhoodcorrelation.org
Classifier: Programming Language :: Python :: 3
Classifier: License :: OSI Approved :: GNU General Public License v3 (GPLv3)
Classifier: Operating System :: OS Independent
Classifier: Topic :: Scientific/Engineering :: Bio-Informatics
License-File: LICENSE
Requires-Dist: numpy
